rn_installer/__init__.py
rn_installer/cli.py
cgsoftech_rn_installer-0.1.dist-info/METADATA
cgsoftech_rn_installer-0.1.dist-info/WHEEL
cgsoftech_rn_installer-0.1.dist-info/entry_points.txt
cgsoftech_rn_installer-0.1.dist-info/top_level.txt
cgsoftech_rn_installer-0.1.dist-info/RECORD
